Phi/__init__.py
Phi/adjbox.py
Phi/finished_methods.py
Phi/mc.dll
Phi/mc_mac.so
Phi/phi.dll
Phi/phi_linux.so
Phi/phi_mac.so
Phi/data/accel_data.cvs
Phi/data/dfs_fixed.cvs
IRonPyt-0.2.9.dist-info/LICENSE
IRonPyt-0.2.9.dist-info/METADATA
IRonPyt-0.2.9.dist-info/WHEEL
IRonPyt-0.2.9.dist-info/top_level.txt
IRonPyt-0.2.9.dist-info/RECORD
