Metadata-Version: 2.1
Name: IRonPyt
Version: 0.2.9
Summary: A sample test package
Home-page: https://github.com/gituser/test-tackage
Author: berre
Author-email: berreergunn@gmail.com
License: MIT
Platform: UNKNOWN
Requires-Python: >=2
License-File: LICENSE
Requires-Dist: matplotlib
Requires-Dist: numpy
Requires-Dist: pandas
Requires-Dist: sklearn
Requires-Dist: pywin32 (>=1.0) ; platform_system == "Windows"
